ras_stac/ras_geom_hdf.py
ras_stac/ras_plan_dg.py
ras_stac/ras_plan_hdf.py
ras_stac/utils/common.py
ras_stac/utils/data_model.py
ras_stac/utils/dg_utils.py
ras_stac/utils/ras_hdf.py
ras_stac/utils/ras_stac.py
ras_stac/utils/s3_utils.py
ras_stac-0.1.1b1.dist-info/LICENSE
ras_stac-0.1.1b1.dist-info/METADATA
ras_stac-0.1.1b1.dist-info/WHEEL
ras_stac-0.1.1b1.dist-info/top_level.txt
ras_stac-0.1.1b1.dist-info/RECORD
