Metadata-Version: 2.1
Name: ras-stac
Version: 0.1.1b1
Summary: Create SpatioTemporal Asset Catalog (STAC) objects from HEC-RAS model data.
Maintainer-email: Seth Lawler <slawler@dewberry.com>
License: MIT
Project-URL: repository, https://github.com/fema-ffrd/ras-stac
Keywords: hec-ras,catalog,STAC
Classifier: Development Status :: 4 - Beta
Classifier: Intended Audience :: Developers
Classifier: License :: OSI Approved :: MIT License
Classifier: Programming Language :: Python :: 3
Classifier: Programming Language :: Python :: 3.9
Classifier: Programming Language :: Python :: 3.10
Classifier: Programming Language :: Python :: 3.11
Classifier: Programming Language :: Python :: 3.12
Requires-Python: >=3.9
License-File: LICENSE
Requires-Dist: boto3
Requires-Dist: botocore
Requires-Dist: fsspec
Requires-Dist: mypy
Requires-Dist: numpy
Requires-Dist: papipyplug
Requires-Dist: python-dotenv
Requires-Dist: pystac
Requires-Dist: shapely
Requires-Dist: rasterio
Requires-Dist: rashdf
Provides-Extra: dev
Requires-Dist: pre-commit ; extra == 'dev'
Requires-Dist: ruff ; extra == 'dev'
